atmclient/__init__.py
atmclient/contrib/__init__.py
atmclient-0.1.3.dist-info/METADATA
atmclient-0.1.3.dist-info/WHEEL
atmclient-0.1.3.dist-info/top_level.txt
atmclient-0.1.3.dist-info/RECORD
