Metadata-Version: 2.1
Name: atmclient
Version: 0.1.3
Summary: ATM v2 API Protocol Compliant Client
Home-page: https://www.lxper.com
Author: LXPER
Author-email: lxpermanager@naver.com
License: UNKNOWN
Platform: UNKNOWN
Classifier: Programming Language :: Python :: 3
Classifier: License :: OSI Approved :: MIT License
Classifier: Operating System :: OS Independent
Requires-Python: >=3.6
Requires-Dist: requests (>=2.10.0)
Requires-Dist: PyYaml (>=5.2.0)
Requires-Dist: easydict (>=1.8)
Requires-Dist: pydantic (>=1.5.0)
